{"version":2,"features":[{"name":"OilResource","id":1,"position":[576,576],"rotation":0},{"name":"OilResource","id":2,"position":[576,704],"rotation":0},{"name":"OilResource","id":3,"position":[704,576],"rotation":0},{"name":"OilResource","id":4,"position":[704,704],"rotation":0},{"name":"OilResource","id":5,"position":[1088,1088],"rotation":0},{"name":"OilResource","id":6,"position":[1088,1344],"rotation":0},{"name":"OilResource","id":7,"position":[1088,1472],"rotation":0},{"name":"OilResource","id":8,"position":[1088,1728],"rotation":0},{"name":"OilResource","id":9,"position":[1344,1728],"rotation":0},{"name":"OilResource","id":10,"position":[1344,1472],"rotation":0},{"name":"OilResource","id":11,"position":[1344,1344],"rotation":0},{"name":"OilResource","id":12,"position":[1344,1088],"rotation":0},{"name":"OilResource","id":13,"position":[1472,1088],"rotation":0},{"name":"OilResource","id":14,"position":[1472,1344],"rotation":0},{"name":"OilResource","id":15,"position":[1472,1472],"rotation":0},{"name":"OilResource","id":16,"position":[1472,1728],"rotation":0},{"name":"OilResource","id":17,"position":[1728,1728],"rotation":0},{"name":"OilResource","id":18,"position":[1728,1472],"rotation":0},{"name":"OilResource","id":19,"position":[1728,1344],"rotation":0},{"name":"OilResource","id":20,"position":[1728,1088],"rotation":0},{"name":"OilResource","id":21,"position":[6464,3904],"rotation":0},{"name":"OilResource","id":22,"position":[6592,3904],"rotation":0},{"name":"OilResource","id":23,"position":[3776,6464],"rotation":0},{"name":"OilResource","id":24,"position":[3776,6592],"rotation":0},{"name":"OilResource","id":187,"position":[1088,10432],"rotation":0},{"name":"OilResource","id":25,"position":[6848,6976],"rotation":0},{"name":"OilResource","id":27,"position":[6976,6976],"rotation":0},{"name":"OilResource","id":26,"position":[6976,6848],"rotation":0},{"name":"OilResource","id":28,"position":[6976,7104],"rotation":0},{"name":"OilResource","id":30,"position":[10304,576],"rotation":0},{"name":"OilResource","id":31,"position":[10304,704],"rotation":0},{"name":"OilResource","id":32,"position":[10432,576],"rotation":0},{"name":"OilResource","id":33,"position":[10432,704],"rotation":0},{"name":"OilResource","id":34,"position":[10048,1088],"rotation":0},{"name":"OilResource","id":35,"position":[10304,1088],"rotation":0},{"name":"OilResource","id":36,"position":[10432,1088],"rotation":0},{"name":"OilResource","id":37,"position":[10688,1088],"rotation":0},{"name":"OilResource","id":38,"position":[10688,1344],"rotation":0},{"name":"OilResource","id":39,"position":[10432,1344],"rotation":0},{"name":"OilResource","id":40,"position":[10304,1344],"rotation":0},{"name":"OilResource","id":41,"position":[10048,1344],"rotation":0},{"name":"OilResource","id":42,"position":[10048,1472],"rotation":0},{"name":"OilResource","id":43,"position":[10304,1472],"rotation":0},{"name":"OilResource","id":44,"position":[10432,1472],"rotation":0},{"name":"OilResource","id":45,"position":[10688,1472],"rotation":0},{"name":"OilResource","id":46,"position":[10688,1728],"rotation":0},{"name":"OilResource","id":47,"position":[10432,1728],"rotation":0},{"name":"OilResource","id":48,"position":[10304,1728],"rotation":0},{"name":"OilResource","id":49,"position":[10048,1728],"rotation":0},{"name":"OilResource","id":29,"position":[7104,6976],"rotation":0},{"name":"OilResource","id":51,"position":[10432,5568],"rotation":0},{"name":"OilResource","id":50,"position":[10304,5568],"rotation":0},{"name":"OilResource","id":156,"position":[6976,13888],"rotation":0},{"name":"OilResource","id":189,"position":[1344,10688],"rotation":0},{"name":"OilResource","id":177,"position":[704,20032],"rotation":0},{"name":"OilResource","id":188,"position":[1088,10688],"rotation":0},{"name":"OilResource","id":190,"position":[1472,10688],"rotation":0},{"name":"OilResource","id":198,"position":[1472,10304],"rotation":0},{"name":"OilResource","id":197,"position":[1344,10304],"rotation":0},{"name":"OilResource","id":196,"position":[1344,10048],"rotation":0},{"name":"OilResource","id":195,"position":[1472,10048],"rotation":0},{"name":"OilResource","id":200,"position":[1344,10432],"rotation":0},{"name":"OilResource","id":199,"position":[1472,10432],"rotation":0},{"name":"OilResource","id":194,"position":[1728,10048],"rotation":0},{"name":"OilResource","id":193,"position":[1728,10304],"rotation":0},{"name":"OilResource","id":192,"position":[1728,10432],"rotation":0},{"name":"OilResource","id":191,"position":[1728,10688],"rotation":0},{"name":"OilResource","id":319,"position":[18368,13888],"rotation":0},{"name":"OilResource","id":318,"position":[24768,20032],"rotation":0},{"name":"OilResource","id":317,"position":[24768,20160],"rotation":0},{"name":"OilResource","id":316,"position":[24640,20160],"rotation":0},{"name":"OilResource","id":186,"position":[1088,10304],"rotation":0},{"name":"OilResource","id":185,"position":[1088,10048],"rotation":0},{"name":"OilResource","id":184,"position":[704,10432],"rotation":0},{"name":"OilResource","id":173,"position":[1728,19392],"rotation":0},{"name":"OilResource","id":183,"position":[704,10304],"rotation":0},{"name":"OilResource","id":182,"position":[576,10432],"rotation":0},{"name":"OilResource","id":181,"position":[576,10304],"rotation":0},{"name":"OilResource","id":180,"position":[576,20160],"rotation":0},{"name":"OilResource","id":179,"position":[576,20032],"rotation":0},{"name":"OilResource","id":178,"position":[704,20160],"rotation":0},{"name":"OilResource","id":176,"position":[1344,19648],"rotation":0},{"name":"OilResource","id":175,"position":[1472,19648],"rotation":0},{"name":"OilResource","id":174,"position":[1728,19648],"rotation":0},{"name":"OilResource","id":170,"position":[1472,19264],"rotation":0},{"name":"OilResource","id":172,"position":[1728,19264],"rotation":0},{"name":"OilResource","id":171,"position":[1472,19392],"rotation":0},{"name":"OilResource","id":169,"position":[1344,19392],"rotation":0},{"name":"OilResource","id":168,"position":[1344,19264],"rotation":0},{"name":"OilResource","id":167,"position":[1088,19648],"rotation":0},{"name":"OilResource","id":166,"position":[1088,19392],"rotation":0},{"name":"OilResource","id":130,"position":[10688,19008],"rotation":0},{"name":"OilResource","id":131,"position":[10432,19008],"rotation":0},{"name":"OilResource","id":132,"position":[10304,19008],"rotation":0},{"name":"OilResource","id":133,"position":[10048,19008],"rotation":0},{"name":"OilResource","id":134,"position":[10048,19264],"rotation":0},{"name":"OilResource","id":135,"position":[10048,19392],"rotation":0},{"name":"OilResource","id":136,"position":[10304,19264],"rotation":0},{"name":"OilResource","id":137,"position":[10304,19392],"rotation":0},{"name":"OilResource","id":138,"position":[10432,19264],"rotation":0},{"name":"OilResource","id":139,"position":[10432,19392],"rotation":0},{"name":"OilResource","id":140,"position":[10688,19264],"rotation":0},{"name":"OilResource","id":141,"position":[10688,19392],"rotation":0},{"name":"OilResource","id":142,"position":[10688,19648],"rotation":0},{"name":"OilResource","id":143,"position":[10432,19648],"rotation":0},{"name":"OilResource","id":144,"position":[10304,19648],"rotation":0},{"name":"OilResource","id":145,"position":[10048,19648],"rotation":0},{"name":"OilResource","id":146,"position":[10304,20032],"rotation":0},{"name":"OilResource","id":147,"position":[10304,20160],"rotation":0},{"name":"OilResource","id":148,"position":[10432,20160],"rotation":0},{"name":"OilResource","id":149,"position":[10432,20032],"rotation":0},{"name":"OilResource","id":150,"position":[10304,15168],"rotation":0},{"name":"OilResource","id":151,"position":[10432,15168],"rotation":0},{"name":"OilResource","id":152,"position":[6976,13632],"rotation":0},{"name":"OilResource","id":154,"position":[6976,13760],"rotation":0},{"name":"OilResource","id":153,"position":[6848,13760],"rotation":0},{"name":"OilResource","id":155,"position":[7104,13760],"rotation":0},{"name":"OilResource","id":157,"position":[3776,14144],"rotation":0},{"name":"OilResource","id":158,"position":[3776,14272],"rotation":0},{"name":"OilResource","id":159,"position":[6464,16832],"rotation":0},{"name":"OilResource","id":160,"position":[6592,16832],"rotation":0},{"name":"OilResource","id":161,"position":[1728,19008],"rotation":0},{"name":"OilResource","id":162,"position":[1472,19008],"rotation":0},{"name":"OilResource","id":163,"position":[1344,19008],"rotation":0},{"name":"OilResource","id":164,"position":[1088,19008],"rotation":0},{"name":"OilResource","id":165,"position":[1088,19264],"rotation":0},{"name":"OilResource","id":242,"position":[18240,6976],"rotation":0},{"name":"OilResource","id":243,"position":[18368,6976],"rotation":0},{"name":"OilResource","id":244,"position":[18368,6848],"rotation":0},{"name":"OilResource","id":245,"position":[18368,7104],"rotation":0},{"name":"OilResource","id":246,"position":[18752,3904],"rotation":0},{"name":"OilResource","id":247,"position":[18880,3904],"rotation":0},{"name":"OilResource","id":248,"position":[24640,576],"rotation":0},{"name":"OilResource","id":249,"position":[24768,576],"rotation":0},{"name":"OilResource","id":250,"position":[24640,704],"rotation":0},{"name":"OilResource","id":251,"position":[24768,704],"rotation":0},{"name":"OilResource","id":252,"position":[24256,1088],"rotation":0},{"name":"OilResource","id":253,"position":[24000,1088],"rotation":0},{"name":"OilResource","id":254,"position":[23872,1088],"rotation":0},{"name":"OilResource","id":255,"position":[23616,1088],"rotation":0},{"name":"OilResource","id":256,"position":[23616,1344],"rotation":0},{"name":"OilResource","id":257,"position":[23616,1472],"rotation":0},{"name":"OilResource","id":258,"position":[23616,1728],"rotation":0},{"name":"OilResource","id":259,"position":[23872,1344],"rotation":0},{"name":"OilResource","id":260,"position":[23872,1472],"rotation":0},{"name":"OilResource","id":261,"position":[24000,1344],"rotation":0},{"name":"OilResource","id":262,"position":[24000,1472],"rotation":0},{"name":"OilResource","id":263,"position":[24256,1344],"rotation":0},{"name":"OilResource","id":264,"position":[24256,1472],"rotation":0},{"name":"OilResource","id":265,"position":[24256,1728],"rotation":0},{"name":"OilResource","id":266,"position":[24000,1728],"rotation":0},{"name":"OilResource","id":267,"position":[23872,1728],"rotation":0},{"name":"OilResource","id":268,"position":[21568,6464],"rotation":0},{"name":"OilResource","id":269,"position":[21568,6592],"rotation":0},{"name":"OilResource","id":270,"position":[23616,10048],"rotation":0},{"name":"OilResource","id":271,"position":[23616,10304],"rotation":0},{"name":"OilResource","id":272,"position":[23616,10432],"rotation":0},{"name":"OilResource","id":273,"position":[23616,10688],"rotation":0},{"name":"OilResource","id":274,"position":[23872,10048],"rotation":0},{"name":"OilResource","id":275,"position":[24000,10048],"rotation":0},{"name":"OilResource","id":276,"position":[24256,10048],"rotation":0},{"name":"OilResource","id":277,"position":[24256,10304],"rotation":0},{"name":"OilResource","id":278,"position":[24000,10304],"rotation":0},{"name":"OilResource","id":279,"position":[23872,10304],"rotation":0},{"name":"OilResource","id":280,"position":[23872,10432],"rotation":0},{"name":"OilResource","id":281,"position":[24000,10432],"rotation":0},{"name":"OilResource","id":282,"position":[24256,10432],"rotation":0},{"name":"OilResource","id":283,"position":[24256,10688],"rotation":0},{"name":"OilResource","id":284,"position":[24000,10688],"rotation":0},{"name":"OilResource","id":285,"position":[23872,10688],"rotation":0},{"name":"OilResource","id":286,"position":[24640,10304],"rotation":0},{"name":"OilResource","id":287,"position":[24640,10432],"rotation":0},{"name":"OilResource","id":288,"position":[24768,10304],"rotation":0},{"name":"OilResource","id":289,"position":[24768,10432],"rotation":0},{"name":"OilResource","id":290,"position":[21568,14144],"rotation":0},{"name":"OilResource","id":291,"position":[21568,14272],"rotation":0},{"name":"OilResource","id":292,"position":[18496,6976],"rotation":0},{"name":"OilResource","id":293,"position":[18240,13760],"rotation":0},{"name":"OilResource","id":294,"position":[18368,13632],"rotation":0},{"name":"OilResource","id":295,"position":[18368,13760],"rotation":0},{"name":"OilResource","id":296,"position":[18496,13760],"rotation":0},{"name":"OilResource","id":297,"position":[18752,16832],"rotation":0},{"name":"OilResource","id":298,"position":[18880,16832],"rotation":0},{"name":"OilResource","id":299,"position":[23616,19008],"rotation":0},{"name":"OilResource","id":300,"position":[23616,19264],"rotation":0},{"name":"OilResource","id":301,"position":[23616,19392],"rotation":0},{"name":"OilResource","id":302,"position":[23616,19648],"rotation":0},{"name":"OilResource","id":303,"position":[23872,19264],"rotation":0},{"name":"OilResource","id":304,"position":[24000,19264],"rotation":0},{"name":"OilResource","id":305,"position":[24000,19392],"rotation":0},{"name":"OilResource","id":306,"position":[23872,19392],"rotation":0},{"name":"OilResource","id":307,"position":[23872,19008],"rotation":0},{"name":"OilResource","id":308,"position":[24000,19008],"rotation":0},{"name":"OilResource","id":309,"position":[24256,19008],"rotation":0},{"name":"OilResource","id":310,"position":[24256,19264],"rotation":0},{"name":"OilResource","id":311,"position":[24256,19392],"rotation":0},{"name":"OilResource","id":312,"position":[24256,19648],"rotation":0},{"name":"OilResource","id":313,"position":[24000,19648],"rotation":0},{"name":"OilResource","id":314,"position":[23872,19648],"rotation":0},{"name":"OilResource","id":315,"position":[24640,20032],"rotation":0},{"name":"OilResource","id":334,"position":[14912,576],"rotation":0},{"name":"OilResource","id":335,"position":[14912,704],"rotation":0},{"name":"OilResource","id":336,"position":[15040,576],"rotation":0},{"name":"OilResource","id":337,"position":[15040,704],"rotation":0},{"name":"OilResource","id":338,"position":[14656,1088],"rotation":0},{"name":"OilResource","id":339,"position":[14912,1088],"rotation":0},{"name":"OilResource","id":340,"position":[15040,1088],"rotation":0},{"name":"OilResource","id":341,"position":[15296,1088],"rotation":0},{"name":"OilResource","id":342,"position":[15296,1344],"rotation":0},{"name":"OilResource","id":343,"position":[15040,1344],"rotation":0},{"name":"OilResource","id":344,"position":[14912,1344],"rotation":0},{"name":"OilResource","id":345,"position":[14656,1344],"rotation":0},{"name":"OilResource","id":346,"position":[14656,1472],"rotation":0},{"name":"OilResource","id":347,"position":[14912,1472],"rotation":0},{"name":"OilResource","id":348,"position":[15040,1472],"rotation":0},{"name":"OilResource","id":349,"position":[15296,1472],"rotation":0},{"name":"OilResource","id":350,"position":[15296,1728],"rotation":0},{"name":"OilResource","id":351,"position":[15040,1728],"rotation":0},{"name":"OilResource","id":352,"position":[14912,1728],"rotation":0},{"name":"OilResource","id":353,"position":[14656,1728],"rotation":0},{"name":"OilResource","id":354,"position":[15040,5568],"rotation":0},{"name":"OilResource","id":355,"position":[14912,5568],"rotation":0},{"name":"OilResource","id":519,"position":[22592,2368],"rotation":0},{"name":"OilResource","id":366,"position":[15296,19008],"rotation":0},{"name":"OilResource","id":367,"position":[15040,19008],"rotation":0},{"name":"OilResource","id":368,"position":[14912,19008],"rotation":0},{"name":"OilResource","id":369,"position":[14656,19008],"rotation":0},{"name":"OilResource","id":370,"position":[14656,19264],"rotation":0},{"name":"OilResource","id":371,"position":[14656,19392],"rotation":0},{"name":"OilResource","id":372,"position":[14912,19264],"rotation":0},{"name":"OilResource","id":373,"position":[14912,19392],"rotation":0},{"name":"OilResource","id":374,"position":[15040,19264],"rotation":0},{"name":"OilResource","id":375,"position":[15040,19392],"rotation":0},{"name":"OilResource","id":376,"position":[15296,19264],"rotation":0},{"name":"OilResource","id":377,"position":[15296,19392],"rotation":0},{"name":"OilResource","id":378,"position":[15296,19648],"rotation":0},{"name":"OilResource","id":379,"position":[15040,19648],"rotation":0},{"name":"OilResource","id":380,"position":[14912,19648],"rotation":0},{"name":"OilResource","id":381,"position":[14656,19648],"rotation":0},{"name":"OilResource","id":382,"position":[14912,20032],"rotation":0},{"name":"OilResource","id":383,"position":[14912,20160],"rotation":0},{"name":"OilResource","id":384,"position":[15040,20160],"rotation":0},{"name":"OilResource","id":385,"position":[15040,20032],"rotation":0},{"name":"OilResource","id":386,"position":[14912,15168],"rotation":0},{"name":"OilResource","id":387,"position":[15040,15168],"rotation":0},{"name":"OilResource","id":388,"position":[2752,2368],"rotation":0},{"name":"OilResource","id":389,"position":[2752,2496],"rotation":0},{"name":"OilResource","id":390,"position":[2752,2624],"rotation":0},{"name":"OilResource","id":391,"position":[2624,2752],"rotation":0},{"name":"OilResource","id":392,"position":[2496,2752],"rotation":0},{"name":"OilResource","id":393,"position":[2368,2752],"rotation":0},{"name":"OilResource","id":394,"position":[10048,1216],"rotation":0},{"name":"OilResource","id":395,"position":[10304,1216],"rotation":0},{"name":"OilResource","id":396,"position":[10432,1216],"rotation":0},{"name":"OilResource","id":397,"position":[10688,1216],"rotation":0},{"name":"OilResource","id":398,"position":[10688,1600],"rotation":0},{"name":"OilResource","id":399,"position":[10432,1600],"rotation":0},{"name":"OilResource","id":400,"position":[10304,1600],"rotation":0},{"name":"OilResource","id":401,"position":[10048,1600],"rotation":0},{"name":"OilResource","id":402,"position":[9920,3136],"rotation":0},{"name":"OilResource","id":403,"position":[10048,3136],"rotation":0},{"name":"OilResource","id":404,"position":[10176,3136],"rotation":0},{"name":"OilResource","id":405,"position":[10560,3136],"rotation":0},{"name":"OilResource","id":406,"position":[10688,3136],"rotation":0},{"name":"OilResource","id":407,"position":[10816,3136],"rotation":0},{"name":"OilResource","id":408,"position":[10944,4288],"rotation":0},{"name":"OilResource","id":409,"position":[10560,4288],"rotation":0},{"name":"OilResource","id":410,"position":[10176,4288],"rotation":0},{"name":"OilResource","id":411,"position":[9792,4288],"rotation":0},{"name":"OilResource","id":412,"position":[14656,1216],"rotation":0},{"name":"OilResource","id":413,"position":[14912,1216],"rotation":0},{"name":"OilResource","id":414,"position":[15040,1216],"rotation":0},{"name":"OilResource","id":415,"position":[15296,1216],"rotation":0},{"name":"OilResource","id":416,"position":[15296,1600],"rotation":0},{"name":"OilResource","id":417,"position":[15040,1600],"rotation":0},{"name":"OilResource","id":418,"position":[14912,1600],"rotation":0},{"name":"OilResource","id":419,"position":[14656,1600],"rotation":0},{"name":"OilResource","id":420,"position":[14528,3136],"rotation":0},{"name":"OilResource","id":421,"position":[14656,3136],"rotation":0},{"name":"OilResource","id":422,"position":[14784,3136],"rotation":0},{"name":"OilResource","id":423,"position":[15168,3136],"rotation":0},{"name":"OilResource","id":424,"position":[15296,3136],"rotation":0},{"name":"OilResource","id":425,"position":[15424,3136],"rotation":0},{"name":"OilResource","id":426,"position":[15552,4288],"rotation":0},{"name":"OilResource","id":427,"position":[15168,4288],"rotation":0},{"name":"OilResource","id":428,"position":[14784,4288],"rotation":0},{"name":"OilResource","id":429,"position":[14400,4288],"rotation":0},{"name":"OilResource","id":430,"position":[3136,9920],"rotation":0},{"name":"OilResource","id":431,"position":[3136,10048],"rotation":0},{"name":"OilResource","id":432,"position":[3136,10176],"rotation":0},{"name":"OilResource","id":433,"position":[3136,10560],"rotation":0},{"name":"OilResource","id":434,"position":[3136,10688],"rotation":0},{"name":"OilResource","id":435,"position":[3136,10816],"rotation":0},{"name":"OilResource","id":436,"position":[5824,10176],"rotation":0},{"name":"OilResource","id":437,"position":[5952,10176],"rotation":0},{"name":"OilResource","id":438,"position":[6080,10176],"rotation":0},{"name":"OilResource","id":439,"position":[6208,10176],"rotation":0},{"name":"OilResource","id":440,"position":[6208,10560],"rotation":0},{"name":"OilResource","id":441,"position":[6080,10560],"rotation":0},{"name":"OilResource","id":442,"position":[5952,10560],"rotation":0},{"name":"OilResource","id":443,"position":[5824,10560],"rotation":0},{"name":"OilResource","id":444,"position":[12480,10176],"rotation":0},{"name":"OilResource","id":445,"position":[12480,10560],"rotation":0},{"name":"OilResource","id":446,"position":[12608,10560],"rotation":0},{"name":"OilResource","id":447,"position":[12608,10176],"rotation":0},{"name":"OilResource","id":448,"position":[12736,10176],"rotation":0},{"name":"OilResource","id":449,"position":[12864,10176],"rotation":0},{"name":"OilResource","id":450,"position":[12864,10560],"rotation":0},{"name":"OilResource","id":451,"position":[12736,10560],"rotation":0},{"name":"OilResource","id":452,"position":[19136,10176],"rotation":0},{"name":"OilResource","id":453,"position":[19264,10176],"rotation":0},{"name":"OilResource","id":454,"position":[19392,10176],"rotation":0},{"name":"OilResource","id":455,"position":[19520,10176],"rotation":0},{"name":"OilResource","id":456,"position":[19520,10560],"rotation":0},{"name":"OilResource","id":457,"position":[19392,10560],"rotation":0},{"name":"OilResource","id":458,"position":[19264,10560],"rotation":0},{"name":"OilResource","id":459,"position":[19136,10560],"rotation":0},{"name":"OilResource","id":460,"position":[22208,9920],"rotation":0},{"name":"OilResource","id":461,"position":[22208,10048],"rotation":0},{"name":"OilResource","id":462,"position":[22208,10176],"rotation":0},{"name":"OilResource","id":463,"position":[22208,10560],"rotation":0},{"name":"OilResource","id":464,"position":[22208,10688],"rotation":0},{"name":"OilResource","id":465,"position":[22208,10816],"rotation":0},{"name":"OilResource","id":466,"position":[22976,17984],"rotation":0},{"name":"OilResource","id":467,"position":[22848,17984],"rotation":0},{"name":"OilResource","id":468,"position":[22720,17984],"rotation":0},{"name":"OilResource","id":469,"position":[22592,18112],"rotation":0},{"name":"OilResource","id":470,"position":[22592,18240],"rotation":0},{"name":"OilResource","id":471,"position":[22592,18368],"rotation":0},{"name":"OilResource","id":472,"position":[15296,19136],"rotation":0},{"name":"OilResource","id":473,"position":[15296,19520],"rotation":0},{"name":"OilResource","id":474,"position":[15040,19520],"rotation":0},{"name":"OilResource","id":475,"position":[15040,19136],"rotation":0},{"name":"OilResource","id":476,"position":[14912,19136],"rotation":0},{"name":"OilResource","id":477,"position":[14912,19520],"rotation":0},{"name":"OilResource","id":478,"position":[14656,19520],"rotation":0},{"name":"OilResource","id":479,"position":[14656,19136],"rotation":0},{"name":"OilResource","id":480,"position":[14528,17600],"rotation":0},{"name":"OilResource","id":481,"position":[14656,17600],"rotation":0},{"name":"OilResource","id":482,"position":[14784,17600],"rotation":0},{"name":"OilResource","id":483,"position":[15168,17600],"rotation":0},{"name":"OilResource","id":484,"position":[15296,17600],"rotation":0},{"name":"OilResource","id":485,"position":[15424,17600],"rotation":0},{"name":"OilResource","id":486,"position":[15552,16448],"rotation":0},{"name":"OilResource","id":487,"position":[15168,16448],"rotation":0},{"name":"OilResource","id":488,"position":[14784,16448],"rotation":0},{"name":"OilResource","id":489,"position":[14400,16448],"rotation":0},{"name":"OilResource","id":490,"position":[10688,19136],"rotation":0},{"name":"OilResource","id":491,"position":[10432,19136],"rotation":0},{"name":"OilResource","id":492,"position":[10304,19136],"rotation":0},{"name":"OilResource","id":493,"position":[10048,19136],"rotation":0},{"name":"OilResource","id":494,"position":[10048,19520],"rotation":0},{"name":"OilResource","id":495,"position":[10304,19520],"rotation":0},{"name":"OilResource","id":496,"position":[10432,19520],"rotation":0},{"name":"OilResource","id":497,"position":[10688,19520],"rotation":0},{"name":"OilResource","id":498,"position":[9920,17600],"rotation":0},{"name":"OilResource","id":499,"position":[10048,17600],"rotation":0},{"name":"OilResource","id":500,"position":[10176,17600],"rotation":0},{"name":"OilResource","id":501,"position":[10560,17600],"rotation":0},{"name":"OilResource","id":502,"position":[10688,17600],"rotation":0},{"name":"OilResource","id":503,"position":[10816,17600],"rotation":0},{"name":"OilResource","id":504,"position":[10944,16448],"rotation":0},{"name":"OilResource","id":505,"position":[10560,16448],"rotation":0},{"name":"OilResource","id":506,"position":[10176,16448],"rotation":0},{"name":"OilResource","id":507,"position":[9792,16448],"rotation":0},{"name":"OilResource","id":508,"position":[2752,18368],"rotation":0},{"name":"OilResource","id":509,"position":[2752,18240],"rotation":0},{"name":"OilResource","id":510,"position":[2752,18112],"rotation":0},{"name":"OilResource","id":511,"position":[2624,17984],"rotation":0},{"name":"OilResource","id":512,"position":[2496,17984],"rotation":0},{"name":"OilResource","id":513,"position":[2368,17984],"rotation":0},{"name":"OilResource","id":514,"position":[22976,2752],"rotation":0},{"name":"OilResource","id":515,"position":[22848,2752],"rotation":0},{"name":"OilResource","id":516,"position":[22720,2752],"rotation":0},{"name":"OilResource","id":517,"position":[22592,2624],"rotation":0},{"name":"OilResource","id":518,"position":[22592,2496],"rotation":0}]}